emailnator/__init__.py
emailnator/version.py
emailnator/asyncio/__init__.py
emailnator/asyncio/email_generator.py
emailnator/asyncio/generators.py
emailnator/asyncio/message_getter.py
emailnator/asyncio/builders/__init__.py
emailnator/asyncio/builders/builders.py
emailnator/asyncio/builders/helpers/__init__.py
emailnator/asyncio/builders/helpers/metaclass.py
emailnator/asyncio/builders/helpers/xsrf_token_service.py
emailnator/asyncio/helpers/__init__.py
emailnator/asyncio/helpers/metaclass.py
emailnator/asyncio/helpers/parser.py
emailnator/config/__init__.py
emailnator/config/config.py
emailnator/config/config.yaml
emailnator/config/helpers.py
emailnator/helpers/__init__.py
emailnator/helpers/logger.py
emailnator/sync/__init__.py
emailnator/sync/email_generator.py
emailnator/sync/email_generator.pyi
emailnator_wrapper-2.1.0.dist-info/licenses/LICENSE.txt
emailnator_wrapper-2.1.0.dist-info/METADATA
emailnator_wrapper-2.1.0.dist-info/WHEEL
emailnator_wrapper-2.1.0.dist-info/top_level.txt
emailnator_wrapper-2.1.0.dist-info/RECORD
