Metadata-Version: 2.4
Name: emailnator-wrapper
Version: 2.1.0
Summary: A Python wrapper for the Emailnator service providing both synchronous and asynchronous APIs.
Author: unelected
License-Expression: AGPL-3.0-or-later
Project-URL: Homepage, https://github.com/unelected/emailnator-wrapper
Project-URL: Repository, https://github.com/unelected/emailnator-wrapper.git
Keywords: email generator,emailnator,gmailnator,gmail generator,gmail,email,tempmail,api,temporary,generator,emailnator api,gmailnator api,web api,web,bulk emails,emails,mail,mail generator
Classifier: Development Status :: 5 - Production/Stable
Classifier: Environment :: Console
Classifier: Intended Audience :: Developers
Requires-Python: >=3.10
License-File: LICENSE.txt
Requires-Dist: httpx~=0.28.1
Requires-Dist: pyyaml~=6.0.2
Provides-Extra: test
Requires-Dist: pytest>=8.0; extra == "test"
Requires-Dist: pytest-asyncio>=1.0; extra == "test"
Requires-Dist: coverage; extra == "test"
Dynamic: license-file
